odoo/addons/pos_show_config_name/README.rst
odoo/addons/pos_show_config_name/__init__.py
odoo/addons/pos_show_config_name/__manifest__.py
odoo/addons/pos_show_config_name/i18n/it.po
odoo/addons/pos_show_config_name/i18n/pos_show_config_name.pot
odoo/addons/pos_show_config_name/readme/DESCRIPTION.rst
odoo/addons/pos_show_config_name/static/description/icon.png
odoo/addons/pos_show_config_name/static/description/index.html
odoo/addons/pos_show_config_name/static/src/xml/CashierName.xml
odoo14_addon_pos_show_config_name-14.0.1.0.1.dev5.dist-info/METADATA
odoo14_addon_pos_show_config_name-14.0.1.0.1.dev5.dist-info/WHEEL
odoo14_addon_pos_show_config_name-14.0.1.0.1.dev5.dist-info/top_level.txt
odoo14_addon_pos_show_config_name-14.0.1.0.1.dev5.dist-info/RECORD
